MANIFEST.in
setup.py
Marmir.egg-info/PKG-INFO
Marmir.egg-info/SOURCES.txt
Marmir.egg-info/dependency_links.txt
Marmir.egg-info/top_level.txt
mm/__init__.py
mm/color_converter.py
mm/composer_base.py
mm/composer_xls.py
mm/config_base.py
mm/document_base.py
mm/document_writers.py
mm/grid_base.py
mm/model_base.py
mm/serializer_base.py
mm/style_base.py
mm/contrib/__init__.py
mm/contrib/django/__init__.py
mm/contrib/django/data_model.py
mm/contrib/django/grid.py
mm/lib/__init__.py
mm/lib/font_data/__init__.py
mm/lib/font_data/core.py
mm/lib/font_data/decorators.py
mm/lib/font_data/font_data_ms_fonts.bin
mm/lib/font_data/tests.py
mm/lib/xldate/__init__.py
mm/lib/xldate/convert.py
mm/lib/xldate/tests.py
mm/lib/xlwt_0_7_2/BIFFRecords.py
mm/lib/xlwt_0_7_2/Bitmap.py
mm/lib/xlwt_0_7_2/Cell.py
mm/lib/xlwt_0_7_2/Column.py
mm/lib/xlwt_0_7_2/CompoundDoc.py
mm/lib/xlwt_0_7_2/ExcelFormula.py
mm/lib/xlwt_0_7_2/ExcelFormulaLexer.py
mm/lib/xlwt_0_7_2/ExcelFormulaParser.py
mm/lib/xlwt_0_7_2/ExcelMagic.py
mm/lib/xlwt_0_7_2/Formatting.py
mm/lib/xlwt_0_7_2/Row.py
mm/lib/xlwt_0_7_2/Style.py
mm/lib/xlwt_0_7_2/UnicodeUtils.py
mm/lib/xlwt_0_7_2/Utils.py
mm/lib/xlwt_0_7_2/Workbook.py
mm/lib/xlwt_0_7_2/Worksheet.py
mm/lib/xlwt_0_7_2/__init__.py
mm/lib/xlwt_0_7_2/antlr.py
mm/lib/xlwt_0_7_2/licences.py