Metadata-Version: 1.0
Name: Marmir
Version: 0.1.2
Summary: Marmir: makes spreadsheets easy
Home-page: http://brianray.github.com/mm
Author: Brian Ray
Author-email: brianhray@gmail.com
License: UNKNOWN
Platform: any
